tterminal/__init__.py
tterminal/main.py
tterminal/models.py
tterminal/styles.css
tterminal-0.1.0.dist-info/licenses/LICENSE
tterminal-0.1.0.dist-info/METADATA
tterminal-0.1.0.dist-info/WHEEL
tterminal-0.1.0.dist-info/entry_points.txt
tterminal-0.1.0.dist-info/top_level.txt
tterminal-0.1.0.dist-info/RECORD
