Metadata-Version: 2.4
Name: tterminal
Version: 0.1.0
Summary: A TUI kanban TODO list with priority classification
Author-email: Haxors <hanzhaxors@gmail.com>
License: MIT
Project-URL: Homepage, https://github.com/HanzCEO/t
Project-URL: Repository, https://github.com/HanzCEO/t
Classifier: Development Status :: 3 - Alpha
Classifier: Environment :: Console
Classifier: Intended Audience :: End Users/Desktop
Classifier: License :: OSI Approved :: MIT License
Classifier: Operating System :: OS Independent
Classifier: Programming Language :: Python :: 3
Classifier: Programming Language :: Python :: 3.8
Classifier: Programming Language :: Python :: 3.9
Classifier: Programming Language :: Python :: 3.10
Classifier: Programming Language :: Python :: 3.11
Classifier: Programming Language :: Python :: 3.12
Classifier: Topic :: Office/Business :: Scheduling
Classifier: Topic :: Terminals
Requires-Python: >=3.8
License-File: LICENSE
Requires-Dist: textual>=0.41.0
Dynamic: license-file
